PyBliss.py
_graph.cpython-38-x86_64-linux-gnu.so
pybliss_wyattpeak-0.1.3.dist-info/METADATA
pybliss_wyattpeak-0.1.3.dist-info/WHEEL
pybliss_wyattpeak-0.1.3.dist-info/top_level.txt
pybliss_wyattpeak-0.1.3.dist-info/RECORD
pybliss_wyattpeak-0.1.3.dist-info/LICENSE.txt
