Metadata-Version: 2.1
Name: pybliss-wyattpeak
Version: 0.1.3
Summary: A Python wrapper for Bliss
Home-page: https://github.com/wyattpeak/pybliss
Author: Wyatt Peak
Author-email: wyatt@wyattpeak.com
License: UNKNOWN
Platform: UNKNOWN
Classifier: Programming Language :: Python :: 3
Classifier: License :: OSI Approved :: GNU General Public License v2 (GPLv2)
Classifier: Operating System :: POSIX :: Linux
Classifier: Operating System :: Microsoft :: Windows
